pp.py
ppauto.py
ppcommon.py
pptransport.py
ppworker.py
pp_for_radvel-1.6.4.6.data/scripts/ppserver.py
pp_for_radvel-1.6.4.6.dist-info/DESCRIPTION.rst
pp_for_radvel-1.6.4.6.dist-info/METADATA
pp_for_radvel-1.6.4.6.dist-info/RECORD
pp_for_radvel-1.6.4.6.dist-info/WHEEL
pp_for_radvel-1.6.4.6.dist-info/metadata.json
pp_for_radvel-1.6.4.6.dist-info/top_level.txt
