Metadata-Version: 2.0
Name: pp-for-radvel
Version: 1.6.4.6
Summary: Parallel and distributed programming for Python
Home-page: http://www.parallelpython.com
Author: Vitalii Vanovschi
Author-email: support@parallelpython.com
License: BSD-like
Download-URL: http://dev.danse.us/packages/
Platform: Windows
Platform: Linux
Platform: Unix
Classifier: Topic :: Software Development
Classifier: Topic :: System :: Distributed Computing
Classifier: Programming Language :: Python
Classifier: Operating System :: OS Independent
Classifier: License :: OSI Approved :: BSD License
Classifier: Natural Language :: English
Classifier: Intended Audience :: Developers
Classifier: Development Status :: 5 - Production/Stable
